LICENSE.txt
MANIFEST.in
README.md
Win32Hooking.py
config.json
pyproject.toml
requirements.txt
setup.cfg
setup.py
Win32Hooking.egg-info/PKG-INFO
Win32Hooking.egg-info/SOURCES.txt
Win32Hooking.egg-info/dependency_links.txt
Win32Hooking.egg-info/entry_points.txt
Win32Hooking.egg-info/requires.txt
Win32Hooking.egg-info/top_level.txt