Metadata-Version: 2.2
Name: Win32Hooking
Version: 1.2.0
Summary: This module hooks IAT and EAT to monitor all external functions calls, very useful for [malware] reverse and debugging.
Home-page: https://github.com/mauricelambert/Win32Hooking
Download-URL: https://mauricelambert.github.io/info/python/security/Win32Hooking.pyz
Author: Maurice Lambert
Author-email: Maurice Lambert <mauricelambert434@gmail.com>
Maintainer: Maurice Lambert
Maintainer-email: Maurice Lambert <mauricelambert434@gmail.com>
License: GPL-3.0 License
Project-URL: Github, https://github.com/mauricelambert/Win32Hooking
Project-URL: Documentation, https://mauricelambert.github.io/info/python/security/Win32Hooking.html
Project-URL: Python Executable, https://mauricelambert.github.io/info/python/security/Win32Hooking.pyz
Project-URL: Windows Executable, https://mauricelambert.github.io/info/python/security/Win32Hooking.exe
Keywords: reverse,win32,winapi,hook,iat,eat,hooking,api-hooking,malware-reverse,hook-import,hook-export,debugging
Platform: Windows
Platform: Linux
Platform: MacOS
Classifier: Topic :: System
Classifier: Topic :: Security
Classifier: Environment :: Console
Classifier: Topic :: System :: Shells
Classifier: Natural Language :: English
Classifier: Programming Language :: Python
Classifier: Intended Audience :: Developers
Classifier: Topic :: System :: System Shells
Classifier: Programming Language :: Python :: 3.8
Classifier: Operating System :: Microsoft :: Windows
Classifier: Topic :: System :: Systems Administration
Classifier: Intended Audience :: System Administrators
Classifier: Development Status :: 5 - Production/Stable
Classifier: License :: OSI Approved :: GNU General Public License v3 or later (GPLv3+)
Requires-Python: >=3.8
License-File: LICENSE.txt
Requires-Dist: PyPeLoader>=0.3.0
Requires-Dist: PythonToolsKit>=1.2.4
Dynamic: author
Dynamic: download-url
Dynamic: home-page
Dynamic: maintainer
Dynamic: requires-python
